Metadata-Version: 1.0
Name: libthai-cffi
Version: 1.0.1
Summary: CFFI Binding to libthai
Home-page: https://github.com/whs/libthai-cffi
Author: Manatsawin Hanmongkolchai
Author-email: manatsawin+pypi@gmail.com
License: LGPL
Platform: UNKNOWN
